pingen2sdk/__init__.py
pingen2sdk/api.py
pingen2sdk/error.py
pingen2sdk/incoming_webhook.py
pingen2sdk/oauth.py
pingen2sdk/response.py
pingen2sdk/webhook_event.py
pingen2sdk/api_resources/__init__.py
pingen2sdk/api_resources/batch_events.py
pingen2sdk/api_resources/batches.py
pingen2sdk/api_resources/ebills.py
pingen2sdk/api_resources/emails.py
pingen2sdk/api_resources/file_upload.py
pingen2sdk/api_resources/letter_events.py
pingen2sdk/api_resources/letters.py
pingen2sdk/api_resources/organisations.py
pingen2sdk/api_resources/user_associations.py
pingen2sdk/api_resources/users.py
pingen2sdk/api_resources/webhooks.py
pingen2sdk-2.1.0.dist-info/licenses/LICENSE
pingen2sdk-2.1.0.dist-info/METADATA
pingen2sdk-2.1.0.dist-info/WHEEL
pingen2sdk-2.1.0.dist-info/top_level.txt
pingen2sdk-2.1.0.dist-info/RECORD
