Metadata-Version: 2.4
Name: pingen2sdk
Version: 2.1.0
Summary: Official Python Pingen SDK for API V2
Author-email: Pingen GmbH <info@pingen.com>
License: BSD-3-Clause
Project-URL: Homepage, https://github.com/pingencom/pingen2-sdk-python
Project-URL: Bug Tracker, https://github.com/pingencom/pingen2-sdk-python/issues
Classifier: Development Status :: 5 - Production/Stable
Classifier: Intended Audience :: Developers
Classifier: Natural Language :: English
Classifier: Operating System :: OS Independent
Classifier: Programming Language :: Python
Classifier: Programming Language :: Python :: 3.10
Classifier: Programming Language :: Python :: 3.11
Classifier: Programming Language :: Python :: 3.12
Classifier: Programming Language :: Python :: 3.13
Classifier: Programming Language :: Python :: 3.14
Classifier: Programming Language :: Python :: Implementation :: PyPy
Classifier: Topic :: Software Development :: Libraries :: Python Modules
Requires-Python: >=3.10
License-File: LICENSE
Requires-Dist: requests>=2.31.0
Requires-Dist: typing-extensions
Requires-Dist: response
Dynamic: license-file
